lion_pytorch/__init__.py
lion_pytorch/foreach.py
lion_pytorch/lion_pytorch.py
lion_pytorch/triton.py
lion_pytorch-0.2.2.dist-info/LICENSE
lion_pytorch-0.2.2.dist-info/METADATA
lion_pytorch-0.2.2.dist-info/WHEEL
lion_pytorch-0.2.2.dist-info/top_level.txt
lion_pytorch-0.2.2.dist-info/RECORD
